django2_piston-2.2.3-py3.7-nspkg.pth
piston/authentication.py
piston/authentication.py.bak
piston/decorator.py
piston/decorator.py.bak
piston/doc.py
piston/doc.py.bak
piston/emitters.py
piston/emitters.py.bak
piston/forms.py
piston/forms.py.bak
piston/handler.py
piston/handler.py.bak
piston/handlers_doc.py
piston/managers.py
piston/middleware.py
piston/models.py
piston/models.py.bak
piston/oauth.py
piston/oauth.py.bak
piston/resource.py
piston/resource.py.bak
piston/signals.py
piston/signals.py.bak
piston/store.py
piston/store.py.bak
piston/test.py
piston/test.py.bak
piston/tests.py
piston/tests.py.bak
piston/utils.py
piston/utils.py.bak
piston/validate_jsonp.py
piston/validate_jsonp.py.bak
django2_piston-2.2.3.dist-info/AUTHORS.txt
django2_piston-2.2.3.dist-info/METADATA
django2_piston-2.2.3.dist-info/WHEEL
django2_piston-2.2.3.dist-info/namespace_packages.txt
django2_piston-2.2.3.dist-info/top_level.txt
django2_piston-2.2.3.dist-info/RECORD
