Metadata-Version: 2.1
Name: django2-piston
Version: 2.2.3
Summary: A Django Piston fork to make it compatible to Django 2 and Python 3
Home-page: https://github.com/wilsonchingg/django2-piston
Author: Wilson Ching
Author-email: wilsonchingg96@gmail.com
License: BSD
Download-URL: https://github.com/wilsonchingg/django2-piston
Platform: UNKNOWN
Classifier: Development Status :: 3 - Alpha
Classifier: Framework :: Django
Classifier: Intended Audience :: Developers
Classifier: License :: OSI Approved :: BSD License
Classifier: Operating System :: OS Independent
Classifier: Programming Language :: Python
Classifier: Topic :: Internet :: WWW/HTTP
